stat3255tutorial/__init__.py
stat3255tutorial/add.py
stat3255tutorial-0.2.0.dist-info/METADATA
stat3255tutorial-0.2.0.dist-info/WHEEL
stat3255tutorial-0.2.0.dist-info/top_level.txt
stat3255tutorial-0.2.0.dist-info/RECORD
