Metadata-Version: 2.1
Name: stat3255tutorial
Version: 0.2.0
Summary: Tutorial Python library for STAT 3255
Home-page: UNKNOWN
Author: Anthony Zeimbekakis
Author-email: UNKNOWN
License: license
Platform: UNKNOWN
